q3dviewer/__init__.py
q3dviewer/base_glwidget.py
q3dviewer/base_item.py
q3dviewer/glwidget.py
q3dviewer/viewer.py
q3dviewer/Qt/__init__.py
q3dviewer/custom_items/__init__.py
q3dviewer/custom_items/axis_item.py
q3dviewer/custom_items/cloud_io_item.py
q3dviewer/custom_items/cloud_item.py
q3dviewer/custom_items/frame_item.py
q3dviewer/custom_items/gaussian_item.py
q3dviewer/custom_items/grid_item.py
q3dviewer/custom_items/image_item.py
q3dviewer/custom_items/line_item.py
q3dviewer/custom_items/mesh_item.py
q3dviewer/custom_items/text3d_item.py
q3dviewer/custom_items/text_item.py
q3dviewer/shaders/cloud_frag.glsl
q3dviewer/shaders/cloud_vert.glsl
q3dviewer/shaders/gau_frag.glsl
q3dviewer/shaders/gau_prep.glsl
q3dviewer/shaders/gau_vert.glsl
q3dviewer/shaders/mesh_frag.glsl
q3dviewer/shaders/mesh_geom.glsl
q3dviewer/shaders/mesh_vert.glsl
q3dviewer/shaders/sort_by_key.glsl
q3dviewer/tools/__init__.py
q3dviewer/tools/cloud_viewer.py
q3dviewer/tools/example_viewer.py
q3dviewer/tools/film_maker.py
q3dviewer/tools/gaussian_viewer.py
q3dviewer/tools/lidar_calib.py
q3dviewer/tools/lidar_cam_calib.py
q3dviewer/tools/ros_viewer.py
q3dviewer/utils/__init__.py
q3dviewer/utils/cloud_io.py
q3dviewer/utils/convert_ros_msg.py
q3dviewer/utils/gl_helper.py
q3dviewer/utils/helpers.py
q3dviewer/utils/maths.py
q3dviewer/utils/range_slider.py
q3dviewer-1.2.3.dist-info/LICENSE
q3dviewer-1.2.3.dist-info/METADATA
q3dviewer-1.2.3.dist-info/WHEEL
q3dviewer-1.2.3.dist-info/entry_points.txt
q3dviewer-1.2.3.dist-info/top_level.txt
q3dviewer-1.2.3.dist-info/RECORD
