Metadata-Version: 2.1
Name: q3dviewer
Version: 1.2.3
Summary: A library designed for quickly deploying a 3D viewer.
Home-page: https://github.com/scomup/q3dviewer
Author: Liu Yang
License: UNKNOWN
Platform: UNKNOWN
Classifier: Programming Language :: Python :: 3
Classifier: License :: OSI Approved :: MIT License
Classifier: Operating System :: OS Independent
Requires-Dist: PyOpenGL
Requires-Dist: imageio
Requires-Dist: imageio[ffmpeg]
Requires-Dist: laspy
Requires-Dist: matplotlib
Requires-Dist: meshio
Requires-Dist: numpy
Requires-Dist: pye57
Requires-Dist: pypcd4
Requires-Dist: pyside6
